argparse.py
setup.py
micropython_argparse.egg-info/PKG-INFO
micropython_argparse.egg-info/SOURCES.txt
micropython_argparse.egg-info/dependency_links.txt
micropython_argparse.egg-info/top_level.txt