Metadata-Version: 1.0
Name: micropython-argparse
Version: 0.4
Summary: argparse module for MicroPython
Home-page: https://github.com/micropython/micropython-lib
Author: micropython-lib Developers
Author-email: micro-python@googlegroups.com
License: MIT
Platform: UNKNOWN
